click_types/__init__.py
click_types/ansible.py
click_types/coding.py
click_types/net.py
click_types-1.0.1.dist-info/LICENSE
click_types-1.0.1.dist-info/METADATA
click_types-1.0.1.dist-info/WHEEL
click_types-1.0.1.dist-info/top_level.txt
click_types-1.0.1.dist-info/RECORD
