Metadata-Version: 2.1
Name: click-types
Version: 1.0.1
Summary: Python library that provides useful click types
Home-page: https://codeaffen.org/projects/click-types/
Author: Christian Meißner
Author-email: Christian Meißner <cme@codeaffen.org>
License: GPLv3
Keywords: click types
Platform: UNKNOWN
Classifier: License :: OSI Approved :: GNU General Public License v3 (GPLv3)
Classifier: Programming Language :: Python :: 3
Classifier: Intended Audience :: Developers
Requires-Python: >=3.6
Requires-Dist: ansible
Requires-Dist: ansible-vault
Requires-Dist: click
Requires-Dist: ipaddress
Requires-Dist: semver
